dataframe2image/__init__.py
dataframe2image/core.py
dataframe2image/styles.py
dataframe2image/template.py
dataframe2image/font/方正兰亭圆简体_准.TTF
dataframe2image/font/方正兰亭圆简体_纤.TTF
dataframe2image-0.2.0.dist-info/licenses/LICENSE
dataframe2image-0.2.0.dist-info/METADATA
dataframe2image-0.2.0.dist-info/WHEEL
dataframe2image-0.2.0.dist-info/top_level.txt
dataframe2image-0.2.0.dist-info/RECORD
