Metadata-Version: 2.4
Name: dataframe2image
Version: 0.2.0
Summary: Convert pandas DataFrame to beautiful table images with automatic Chinese font support
Author-email: nolan zhao <nolanzhao@126.com>
License-Expression: MIT
Project-URL: Homepage, https://github.com/nolanzhao/dataframe2image
Project-URL: Repository, https://github.com/nolanzhao/dataframe2image
Project-URL: Issues, https://github.com/nolanzhao/dataframe2image/issues
Keywords: pandas,dataframe,table,image,screenshot
Classifier: Development Status :: 4 - Beta
Classifier: Intended Audience :: Developers
Classifier: Programming Language :: Python :: 3
Classifier: Programming Language :: Python :: 3.8
Classifier: Programming Language :: Python :: 3.9
Classifier: Programming Language :: Python :: 3.10
Classifier: Programming Language :: Python :: 3.11
Classifier: Programming Language :: Python :: 3.12
Classifier: Topic :: Software Development :: Libraries :: Python Modules
Classifier: Topic :: Utilities
Requires-Python: >=3.8
License-File: LICENSE
Requires-Dist: pandas>=1.3.0
Requires-Dist: playwright>=1.35.0
Requires-Dist: jinja2>=3.0.0
Requires-Dist: pillow>=8.0.0
Provides-Extra: dev
Requires-Dist: pytest>=7.0.0; extra == "dev"
Requires-Dist: pytest-asyncio>=0.21.0; extra == "dev"
Requires-Dist: black>=22.0.0; extra == "dev"
Requires-Dist: isort>=5.10.0; extra == "dev"
Requires-Dist: flake8>=4.0.0; extra == "dev"
Requires-Dist: mypy>=0.991; extra == "dev"
Dynamic: license-file
